distrifuser/__init__.py
distrifuser/__version__.py
distrifuser/pipelines.py
distrifuser/utils.py
distrifuser/models/__init__.py
distrifuser/models/base_model.py
distrifuser/models/distri_sdxl_unet_pp.py
distrifuser/models/distri_sdxl_unet_tp.py
distrifuser/models/naive_patch_sdxl.py
distrifuser/modules/__init__.py
distrifuser/modules/base_module.py
distrifuser/modules/pp/__init__.py
distrifuser/modules/pp/attn.py
distrifuser/modules/pp/conv2d.py
distrifuser/modules/pp/groupnorm.py
distrifuser/modules/tp/__init__.py
distrifuser/modules/tp/attention.py
distrifuser/modules/tp/conv2d.py
distrifuser/modules/tp/feed_forward.py
distrifuser/modules/tp/resnet.py
distrifuser-0.0.1b1.dist-info/LICENSE.txt
distrifuser-0.0.1b1.dist-info/METADATA
distrifuser-0.0.1b1.dist-info/WHEEL
distrifuser-0.0.1b1.dist-info/top_level.txt
distrifuser-0.0.1b1.dist-info/RECORD
