Metadata-Version: 2.1
Name: distrifuser
Version: 0.0.1b1
Summary: DistriFusion: Distributed Parallel Inference for High-Resolution Diffusion Models
Home-page: https://github.com/mit-han-lab/distrifuser
Author: Muyang Li, Tianle Cai, Jiaxin Cao, Qinsheng Zhang, Han Cai, Junjie Bai, Yangqing Jia, Ming-Yu Liu, Kai Li and Song Han
Author-email: muyangli@mit.edu
Classifier: Programming Language :: Python :: 3
Classifier: Operating System :: OS Independent
Requires-Python: >=3.10
License-File: LICENSE.txt
Requires-Dist: torch (>=2.2)
Requires-Dist: diffusers (==0.24.0)
Requires-Dist: transformers
Requires-Dist: tqdm
